universal_edit_distance-0.4.3.dist-info/METADATA
universal_edit_distance-0.4.3.dist-info/WHEEL
universal_edit_distance-0.4.3.dist-info/licenses/LICENSE
universal_edit_distance/__init__.py
universal_edit_distance/__init__.pyi
universal_edit_distance/py.typed
universal_edit_distance/universal_edit_distance.cpython-312-darwin.so
universal_edit_distance-0.4.3.dist-info/RECORD
