Metadata-Version: 2.4
Name: universal_edit_distance
Version: 0.4.3
Classifier: Programming Language :: Rust
Classifier: Programming Language :: Python :: Implementation :: CPython
Classifier: Programming Language :: Python :: Implementation :: PyPy
License-File: LICENSE
Summary: A package containing generic error-rate functions implemented in Rust
Author-email: Preben Vangberg <prv21fgt@bangor.ac.uk>
License-Expression: MIT
Requires-Python: >=3.8
Project-URL: homepage, https://gitlab.com/prebens-phd-adventures/universal-error-rate
Project-URL: repository, https://gitlab.com/prebens-phd-adventures/universal-error-rate
